haystack_integrations/components/generators/py.typed
haystack_integrations/components/generators/meta_llama/__init__.py
haystack_integrations/components/generators/meta_llama/chat/__init__.py
haystack_integrations/components/generators/meta_llama/chat/chat_generator.py
meta_llama_haystack-1.2.0.dist-info/METADATA
meta_llama_haystack-1.2.0.dist-info/WHEEL
meta_llama_haystack-1.2.0.dist-info/licenses/LICENSE.txt
meta_llama_haystack-1.2.0.dist-info/RECORD
